weaver/__init__.py
weaver/artefact_registry.py
weaver/data.py
weaver/reader.py
weaver/registry.py
weaver/resource.py
weaver/serializer.py
weaver/unweave.py
weaver/version.py
weaver/weave.py
weaver_json-0.0.2.dist-info/METADATA
weaver_json-0.0.2.dist-info/WHEEL
weaver_json-0.0.2.dist-info/RECORD
