Metadata-Version: 2.1
Name: weaver-json
Version: 0.0.2
Summary: Serialize and Deserialize Python Classes using JSON
License: LGPL-3.0-or-later
Author: Lissa Hyacinth
Author-email: lissa@shareableai.com
Requires-Python: >=3.10,<3.12
Classifier: License :: OSI Approved :: GNU Lesser General Public License v3 or later (LGPLv3+)
Classifier: Programming Language :: Python :: 3
Classifier: Programming Language :: Python :: 3.10
Classifier: Programming Language :: Python :: 3.11
Requires-Dist: artefactlink (>=0.4.1)
Requires-Dist: pyarrow (>=9,<=12)
